{"_type":"export","__export_format":4,"__export_date":"2022-06-19T02:00:49.069Z","__export_source":"insomnia.desktop.app:v2022.4.0","resources":[{"_id":"req_a1b599a0781941ca98df7cffb7b0b4d4","parentId":"fld_c1e3ab8a7f32416ebf3712531109c965","modified":1655604021192,"created":1655243133655,"url":"http://localhost:3000/dev/person/create ","name":"Create","description":"","method":"POST","body":{"mimeType":"application/json","text":"{\n\t\"name\":\"Jose Fereira\",\n\t\"email\":\"jose@email.com\"\n}"},"parameters":[],"headers":[{"name":"Content-Type","value":"application/json","id":"pair_711d4cf987ac436987cc1d5f3e848013"}],"authentication":{},"metaSortKey":-1655243133655,"isPrivate":false,"settingStoreCookies":true,"settingSendCookies":true,"settingDisableRenderRequestBody":false,"settingEncodeUrl":true,"settingRebuildPath":true,"settingFollowRedirects":"global","_type":"request"},{"_id":"fld_c1e3ab8a7f32416ebf3712531109c965","parentId":"wrk_59d1417a63e740d4bfaf4e88fe3cf341","modified":1655604018336,"created":1655604018336,"name":"CRUD Python+Sls","description":"","environment":{},"environmentPropertyOrder":null,"metaSortKey":-1655604018336,"_type":"request_group"},{"_id":"wrk_59d1417a63e740d4bfaf4e88fe3cf341","parentId":null,"modified":1655243038317,"created":1655243038317,"name":"Estudo Python","description":"","scope":"collection","_type":"workspace"},{"_id":"req_63ff3d41122e445ca1508dbc3da0a2ce","parentId":"fld_c1e3ab8a7f32416ebf3712531109c965","modified":1655604022298,"created":1655578976536,"url":"http://localhost:3000/dev/person/list ","name":"List","description":"","method":"GET","body":{},"parameters":[],"headers":[],"authentication":{},"metaSortKey":-1655243133605,"isPrivate":false,"settingStoreCookies":true,"settingSendCookies":true,"settingDisableRenderRequestBody":false,"settingEncodeUrl":true,"settingRebuildPath":true,"settingFollowRedirects":"global","_type":"request"},{"_id":"req_5c7fe29dc7ff4ccb98ad38d73e110340","parentId":"fld_c1e3ab8a7f32416ebf3712531109c965","modified":1655604023406,"created":1655591248813,"url":"http://localhost:3000/dev/person/show/5e35cb5f8057422eb8a2a7fba9970bfb","name":"Show","description":"","method":"GET","body":{},"parameters":[],"headers":[],"authentication":{},"metaSortKey":-1655243133555,"isPrivate":false,"settingStoreCookies":true,"settingSendCookies":true,"settingDisableRenderRequestBody":false,"settingEncodeUrl":true,"settingRebuildPath":true,"settingFollowRedirects":"global","_type":"request"},{"_id":"req_d5957897ca044a8fa9f71861e831d946","parentId":"fld_c1e3ab8a7f32416ebf3712531109c965","modified":1655604028535,"created":1655593481663,"url":"http://localhost:3000/dev/person/update/5e35cb5f8057422eb8a2a7fba9970bfb","name":"Update","description":"","method":"PUT","body":{"mimeType":"application/json","text":"{\n\t\"name\":\"Jose Silva\",\n\t\"email\":\"jose12@email.com\"\n}"},"parameters":[],"headers":[{"name":"Content-Type","value":"application/json","id":"pair_5f3bbe4caf0143f5b8fa5f7a773f3da9"}],"authentication":{},"metaSortKey":-1655243133530,"isPrivate":false,"settingStoreCookies":true,"settingSendCookies":true,"settingDisableRenderRequestBody":false,"settingEncodeUrl":true,"settingRebuildPath":true,"settingFollowRedirects":"global","_type":"request"},{"_id":"req_5c494900104f471c8365f44641c7bc59","parentId":"fld_c1e3ab8a7f32416ebf3712531109c965","modified":1655604024389,"created":1655595990733,"url":"http://localhost:3000/dev/person/delete/2710bbc687834091975ad8002a156b5f","name":"Delete","description":"","method":"DELETE","body":{},"parameters":[],"headers":[],"authentication":{},"metaSortKey":-1655243133505,"isPrivate":false,"settingStoreCookies":true,"settingSendCookies":true,"settingDisableRenderRequestBody":false,"settingEncodeUrl":true,"settingRebuildPath":true,"settingFollowRedirects":"global","_type":"request"},{"_id":"env_2b5e8012fe8fc60024e301f0280718a358840ace","parentId":"wrk_59d1417a63e740d4bfaf4e88fe3cf341","modified":1655243038322,"created":1655243038322,"name":"Base Environment","data":{},"dataPropertyOrder":null,"color":null,"isPrivate":false,"metaSortKey":1655243038322,"_type":"environment"},{"_id":"jar_2b5e8012fe8fc60024e301f0280718a358840ace","parentId":"wrk_59d1417a63e740d4bfaf4e88fe3cf341","modified":1655243038323,"created":1655243038323,"name":"Default Jar","cookies":[],"_type":"cookie_jar"},{"_id":"spc_aa604c810cb04358ad62ed50553bf83a","parentId":"wrk_59d1417a63e740d4bfaf4e88fe3cf341","modified":1655243038319,"created":1655243038319,"fileName":"Estudo Python","contents":"","contentType":"yaml","_type":"api_spec"}]}